awslabs/__init__.py
awslabs/amazon_bedrock_agentcore_mcp_server/__init__.py
awslabs/amazon_bedrock_agentcore_mcp_server/config.py
awslabs/amazon_bedrock_agentcore_mcp_server/server.py
awslabs/amazon_bedrock_agentcore_mcp_server/tools/__init__.py
awslabs/amazon_bedrock_agentcore_mcp_server/tools/docs.py
awslabs/amazon_bedrock_agentcore_mcp_server/tools/gateway.py
awslabs/amazon_bedrock_agentcore_mcp_server/tools/memory.py
awslabs/amazon_bedrock_agentcore_mcp_server/tools/runtime.py
awslabs/amazon_bedrock_agentcore_mcp_server/utils/__init__.py
awslabs/amazon_bedrock_agentcore_mcp_server/utils/cache.py
awslabs/amazon_bedrock_agentcore_mcp_server/utils/doc_fetcher.py
awslabs/amazon_bedrock_agentcore_mcp_server/utils/indexer.py
awslabs/amazon_bedrock_agentcore_mcp_server/utils/text_processor.py
awslabs/amazon_bedrock_agentcore_mcp_server/utils/url_validator.py
awslabs_amazon_bedrock_agentcore_mcp_server-0.0.12.dist-info/METADATA
awslabs_amazon_bedrock_agentcore_mcp_server-0.0.12.dist-info/WHEEL
awslabs_amazon_bedrock_agentcore_mcp_server-0.0.12.dist-info/entry_points.txt
awslabs_amazon_bedrock_agentcore_mcp_server-0.0.12.dist-info/licenses/LICENSE
awslabs_amazon_bedrock_agentcore_mcp_server-0.0.12.dist-info/licenses/NOTICE
awslabs_amazon_bedrock_agentcore_mcp_server-0.0.12.dist-info/RECORD
